.project
.pydevproject
MANIFEST.in
README.txt
build.sh
settings.py
setup.py
cabig/__init__.py
cabig/__init__.pyc
cabig/cabio/CaBioWSQueryService_client.py
cabig/cabio/CaBioWSQueryService_server.py
cabig/cabio/CaBioWSQueryService_types.py
cabig/cabio/__init__.py
cabig/cabio/domain.py
cabig/cabio/pathways.py
cabig/cabio/service.py
cabig/cabio/common/__init__.py
cabig/cabio/common/domain.py
cabig/cabio/common/provenance/__init__.py
cabig/cabio/common/provenance/domain.py
conf/cabio41.wsdl
conf/cabio42.wsdl
examples/cabio_demo.py
examples/pid_demo.py
examples/stage_demo.py
pyCaBio.egg-info/PKG-INFO
pyCaBio.egg-info/SOURCES.txt
pyCaBio.egg-info/dependency_links.txt
pyCaBio.egg-info/namespace_packages.txt
pyCaBio.egg-info/requires.txt
pyCaBio.egg-info/top_level.txt
tests/__init__.py
tests/__init__.pyc
tests/defects.py
tests/unit_tests.py
tests/unit_tests.pyc