Metadata-Version: 1.0
Name: pyCaBio
Version: 0.5.0
Summary: caBIO Python API
Home-page: http://cabioapi.nci.nih.gov/
Author: Konrad Rokicki
Author-email: rokickik@mail.nih.gov
License: caBIG Open Source Software License
Platform: All
